plusclouds.py
plusclouds-service/__init__.py
plusclouds-service/__main__.py
plusclouds-service/service.py
plusclouds-service/storage.py
plusclouds-service/module_search/__init__.py
plusclouds-service/module_search/ansible_operations.py
plusclouds-service/module_search/callback_agent.py
plusclouds-service/module_search/service_search.py
plusclouds-service/util/__init__.py
plusclouds-service/util/ssh_keys/__init__.py
plusclouds-service/util/ssh_keys/ssh_key_parser.py
plusclouds_service-0.0.6.dist-info/METADATA
plusclouds_service-0.0.6.dist-info/WHEEL
plusclouds_service-0.0.6.dist-info/licenses/LICENSE
plusclouds_service-0.0.6.dist-info/RECORD
