Metadata-Version: 2.1
Name: plusclouds-service
Version: 0.0.6
Summary: Virtual Machine Deployment Agent for PlusClouds ecosystem
Project-URL: Homepage, https://github.com/plusclouds/vmOperations
Project-URL: Bug Tracker, https://github.com/plusclouds/vmOperations/issues
Author-email: Talha Unsel <talha.unsel@plusclouds.com>, Yigithan Saglam <saglamyigithan@gmail.com>, Semih Yonet <semityonet@gmail.com>, Zekican Budin <zekican.budin@plusclouds.com>
License: MIT License
License-File: LICENSE
Classifier: License :: OSI Approved :: MIT License
Classifier: Operating System :: Microsoft :: Windows :: Windows Server 2008
Classifier: Operating System :: POSIX :: Linux
Classifier: Programming Language :: Python :: 3.8
Requires-Python: >=3.8
Requires-Dist: distro==1.8.0
Requires-Dist: requests==2.28.1
